ietf_comments/__init__.py
ietf_comments/github.py
ietf_comments/linkify.py
ietf_comments/ui.py
ietf_comments-0.2.5.dist-info/LICENSE
ietf_comments-0.2.5.dist-info/METADATA
ietf_comments-0.2.5.dist-info/WHEEL
ietf_comments-0.2.5.dist-info/entry_points.txt
ietf_comments-0.2.5.dist-info/top_level.txt
ietf_comments-0.2.5.dist-info/RECORD
