Metadata-Version: 2.1
Name: ietf-comments
Version: 0.2.5
Summary: Automating IETF comment handling
Home-page: https://github.com/mnot/ietf-comments
Author: Mark Nottingham
Author-email: mnot@mnot.net
Project-URL: Bug Tracker, https://github.com/mnot/ietf-comments/issues
Classifier: Operating System :: OS Independent
Classifier: Environment :: Console
Classifier: Programming Language :: Python :: 3.6
Classifier: Development Status :: 4 - Beta
Classifier: License :: OSI Approved :: BSD License
Classifier: Topic :: Text Processing :: Markup :: Markdown
Requires-Python: >=3.6
License-File: LICENSE
Requires-Dist: ietf-comments-engine
Requires-Dist: pygithub
Requires-Dist: blessings
Provides-Extra: dev
Requires-Dist: mypy ; extra == 'dev'
Requires-Dist: black ; extra == 'dev'
